{"stats": [{"H": "Videos", "C": "16"}, {"H": "Movies", "C": "4"}, {"H": "Years", "C": "3"}, {"H": "Duration", "C": "36 H"}, {"H": "Views", "C": "101 M"}], "poster": {"P": "Images/person.jpg"}, "title": {"T": 2277, "H": "Leena Das", "V": "lIna dAs", "I": "person-fill"}, "movies": [{"I": "ts7rdgsoihc", "M": 10024, "Y": 80, "P": 2277, "K": 1185, "D": "2:42:09", "V": "15,038,136", "J": "m", "S": 1084}, {"I": "m8Tm9CKHXq8", "M": 10024, "Y": 80, "P": 2277, "K": 1185, "D": "2:25:46", "V": "1,871,784", "J": "m", "S": 1084}, {"I": "9GhpM9sctqw", "M": 10024, "Y": 80, "P": 2277, "K": 1185, "D": "2:25:54", "V": "986,848", "J": "m", "S": 1084}, {"I": "UDFMQN9D_ho", "M": 10024, "Y": 80, "P": 2277, "K": 1185, "D": "2:17:53", "V": "881,653", "J": "m", "S": 1084}, {"I": "nnmWKTQtTP0", "M": 10024, "Y": 80, "P": 2277, "K": 1185, "D": "1:57:32", "V": "147,107", "J": "m", "S": 1084}, {"I": "FNOnzneRO0c", "M": 10024, "Y": 80, "P": 2277, "K": 1185, "D": "2:23:26", "V": "16,798", "J": "m", "S": 1084}, {"I": "dA2gq3Rv7Is", "M": 10024, "Y": 80, "P": 2277, "K": 1185, "D": "2:08:22", "V": "11,324", "J": "m", "S": 1084}, {"I": "fn_C8gbBY44", "M": 8100, "Y": 88, "P": 2277, "K": 1960, "D": "1:52:52", "V": "151,100", "J": "m", "S": 10523}, {"I": "6vBZw_8Ngr4", "M": 7962, "Y": 88, "P": 2277, "K": 772, "D": "2:06:26", "V": "398,851", "J": "m", "S": 2}, {"I": "LkJ4KPMKnCE", "M": 7962, "Y": 88, "P": 2277, "K": 772, "D": "1:37:26", "V": "150,436", "J": "m", "S": 2}, {"I": "mgl6k16XFXQ", "M": 6320, "Y": 91, "P": 2277, "K": 10005, "D": "2:23:47", "V": "36,649,348", "J": "m", "S": 2}, {"I": "4TASlAqxa1c", "M": 6320, "Y": 91, "P": 2277, "K": 10005, "D": "2:23:47", "V": "20,005,811", "J": "m", "S": 2}, {"I": "4YRrTpHlWVE", "M": 6320, "Y": 91, "P": 2277, "K": 10005, "D": "2:23:47", "V": "12,723,200", "J": "m", "S": 2}, {"I": "D6swx-kCRNM", "M": 6320, "Y": 91, "P": 2277, "K": 10005, "D": "2:23:45", "V": "10,106,182", "J": "m", "S": 2}, {"I": "3DWf2txkJ00", "M": 6320, "Y": 91, "P": 2277, "K": 10005, "D": "2:23:57", "V": "1,396,271", "J": "m", "S": 2}, {"I": "J6L4b0AwwuI", "M": 6320, "Y": 91, "P": 2277, "K": 10005, "D": "2:23:51", "V": "76,090", "J": "m", "S": 2}], "folders": [["movie", 10024, "0,1,2,3,4,5,6"], ["movie", 8100, "7"], ["movie", 7962, "8,9"], ["movie", 6320, "10,11,12,13,14,15"]], "languages": {"english": "0,1,2,3", "tamil": "0,1,2,3", "telugu": "0,1,2,3", "kannada": "0,1,2,3", "malayalam": "0,1,2,3", "hindi": "0,1,2,3", "marathi": "0,1,2,3", "bengali": "0,1,2,3", "gujarati": "0,1,2,3", "punjabi": "0,1,2,3", "odia": "0,1,2,3", "assamese": "0,1,2,3"}}