{"stats": [{"H": "Videos", "C": "87"}, {"H": "Movies", "C": "20"}, {"H": "Years", "C": "15"}, {"H": "Duration", "C": "206 H"}, {"H": "Views", "C": "31 M"}], "poster": {"P": "Images/person.jpg"}, "title": {"H": "Motilal", "V": "motilal", "I": "person-fill"}, "videos": [{"folder": [{"M": 10013, "S": 1145, "movies": [{"D": "2:13:35", "I": "0PhS1knOSYI", "J": "m", "K": 1590, "P": 81, "V": "158,577", "Y": 58, "S": 1145}, {"D": "2:13:35", "I": "hVZJx5yZb30", "J": "s", "K": 1590, "P": 81, "V": "42,940", "Y": 58, "S": 1145}, {"D": "2:13:35", "I": "rNlJt1Rdq4E", "J": "m", "K": 1590, "P": 81, "V": "17,971", "Y": 58, "S": 1145}, {"D": "2:13:35", "I": "Oy-3UHhFb3M", "J": "m", "K": 1590, "P": 81, "V": "4,185", "Y": 58, "S": 1145}, {"D": "2:13:33", "I": "g8F7JIgZx5I", "J": "m", "K": 1590, "P": 81, "V": "1,462", "Y": 58, "S": 1145}]}, {"M": 9973, "S": 81, "movies": [{"D": "2:15:59", "I": "iTr17tLjsxg", "J": "h", "K": 379, "P": 81, "V": "183", "Y": 41, "S": 81}]}, {"M": 9696, "S": 104, "movies": [{"D": "2:36:27", "I": "msnQ73uhyR0", "J": "m", "K": 289, "P": 81, "V": "4,123,063", "Y": 60, "S": 104}, {"D": "2:36:27", "I": "HujdhyUcfrw", "J": "m", "K": 289, "P": 81, "V": "3,417,512", "Y": 60, "S": 104}, {"D": "2:36:31", "I": "5cATeVPJ-ko", "J": "m", "K": 289, "P": 81, "V": "26,622", "Y": 60, "S": 104}, {"D": "2:36:27", "I": "IA1oZFC4wPE", "J": "m", "K": 289, "P": 81, "V": "22,031", "Y": 60, "S": 104}, {"D": "2:36:41", "I": "TYFXnWq_X6o", "J": "h", "K": 289, "P": 81, "V": "7,867", "Y": 60, "S": 104}, {"D": "2:36:31", "I": "laXAHhDCmGg", "J": "m", "K": 289, "P": 81, "V": "6,485", "Y": 60, "S": 104}, {"D": "2:36:32", "I": "P2480tncaec", "J": "m", "K": 289, "P": 81, "V": "5,051", "Y": 60, "S": 104}, {"D": "2:36:38", "I": "6rg8Hc-8HgQ", "J": "m", "K": 289, "P": 81, "V": "4,041", "Y": 60, "S": 104}, {"D": "2:36:31", "I": "Zh6-hVxHMAw", "J": "m", "K": 289, "P": 81, "V": "3,670", "Y": 60, "S": 104}]}, {"M": 9120, "S": 75, "movies": [{"D": "2:17:40", "I": "Qz3U4VhQWaU", "J": "m", "K": 9495, "P": 81, "V": "106,139", "Y": 57, "S": 75}, {"D": "2:20:46", "I": "xTFqWiSz7JE", "J": "m", "K": 9495, "P": 81, "V": "37,487", "Y": 57, "S": 75}, {"D": "1:20:36", "I": "Tcrb0AcXXQs", "J": "m", "K": 9495, "P": 81, "V": "15,455", "Y": 57, "S": 75}, {"D": "2:20:46", "I": "sDli08ZYGrg", "J": "m", "K": 9495, "P": 81, "V": "5,808", "Y": 57, "S": 75}]}, {"M": 8951, "S": 84, "movies": [{"D": "2:10:19", "I": "bP-nkePPxG0", "J": "h", "K": 1990, "P": 81, "V": "16,477", "Y": 53, "S": 84}, {"D": "2:10:05", "I": "1JHEUITaCjo", "J": "m", "K": 1990, "P": 81, "V": "11,315", "Y": 53, "S": 84}, {"D": "2:10:06", "I": "JMGlgGty4Nk", "J": "m", "K": 1990, "P": 81, "V": "9,479", "Y": 53, "S": 84}]}, {"M": 8299, "S": 345, "movies": [{"D": "2:10:02", "I": "PPW9KcyrATk", "J": "h", "K": 81, "P": 81, "V": "79,254", "Y": 66, "S": 345}]}, {"M": 7902, "S": 1430, "movies": [{"D": "2:35:25", "I": "5vTH16nAXhY", "J": "m", "K": 730, "P": 81, "V": "6,871,315", "Y": 56, "S": 1430}, {"D": "2:06:47", "I": "o8iZW-FSIBM", "J": "m", "K": 730, "P": 81, "V": "3,780,159", "Y": 56, "S": 1430}, {"D": "2:48:01", "I": "EPhXAbc3ZmE", "J": "m", "K": 730, "P": 81, "V": "565,321", "Y": 56, "S": 1430}, {"D": "2:35:01", "I": "t7P_xqKfjUA", "J": "m", "K": 730, "P": 81, "V": "221,955", "Y": 56, "S": 1430}, {"D": "2:35:17", "I": "PqTcJncAE5c", "J": "m", "K": 730, "P": 81, "V": "19,324", "Y": 56, "S": 1430}, {"D": "2:47:50", "I": "aEaC5HKh6Pk", "J": "m", "K": 730, "P": 81, "V": "11,125", "Y": 56, "S": 1430}, {"D": "2:47:51", "I": "7fu4t-wkH_Y", "J": "m", "K": 730, "P": 81, "V": "7,861", "Y": 56, "S": 1430}, {"D": "2:47:50", "I": "dHdcQMu4Jw4", "J": "m", "K": 730, "P": 81, "V": "4,190", "Y": 56, "S": 1430}, {"D": "2:47:50", "I": "5V_OgEwAADE", "J": "m", "K": 730, "P": 81, "V": "2,458", "Y": 56, "S": 1430}, {"D": "2:41:35", "I": "YTForPxFZZY", "J": "m", "K": 730, "P": 81, "V": "2,148", "Y": 56, "S": 1430}]}, {"M": 7666, "S": 249, "movies": [{"D": "1:57:34", "I": "BwcojKDfUWU", "J": "m", "K": 153, "P": 81, "V": "23,834", "Y": 41, "S": 249}]}, {"M": 7361, "S": 861, "movies": [{"D": "3:09:21", "I": "ouI6ZRnQp0M", "J": "m", "K": 752, "P": 81, "V": "22,967", "Y": 54, "S": 861}, {"D": "2:26:27", "I": "cVQ1Ju7hcA0", "J": "m", "K": 752, "P": 81, "V": "10,866", "Y": 54, "S": 861}, {"D": "2:20:39", "I": "bQWdbamfpjA", "J": "h", "K": 752, "P": 81, "V": "8,219", "Y": 54, "S": 861}]}, {"M": 7282, "S": 861, "movies": [{"D": "2:49:14", "I": "UA57T609gJo", "J": "m", "K": 752, "P": 81, "V": "18,727", "Y": 50, "S": 861}, {"D": "2:49:14", "I": "IbDZfKxLJFU", "J": "m", "K": 752, "P": 81, "V": "3,420", "Y": 50, "S": 861}, {"D": "2:34:42", "I": "jqrmngTnlHA", "J": "m", "K": 752, "P": 81, "V": "3,144", "Y": 50, "S": 861}]}, {"M": 6645, "S": 104, "movies": [{"D": "1:45:40", "I": "laSuILUGnGw", "J": "m", "K": 257, "P": 81, "V": "42,842", "Y": 51, "S": 104}, {"D": "1:45:58", "I": "Glc_2cEusdQ", "J": "h", "K": 257, "P": 81, "V": "16,937", "Y": 51, "S": 104}]}, {"M": 5993, "S": 81, "movies": [{"D": "2:17:34", "I": "72qLogUlJRQ", "J": "m", "K": 11194, "P": 81, "V": "1,927,990", "Y": 57, "S": 81}, {"D": "2:17:34", "I": "rPy0W3SAXrc", "J": "m", "K": 11194, "P": 81, "V": "456,146", "Y": 57, "S": 81}, {"D": "2:17:33", "I": "zuLU9bRsTJI", "J": "m", "K": 11194, "P": 81, "V": "117,154", "Y": 57, "S": 81}, {"D": "2:23:20", "I": "0lUyhaSQMzU", "J": "m", "K": 11194, "P": 81, "V": "102,969", "Y": 57, "S": 81}, {"D": "2:17:31", "I": "gmXcIa1qlTs", "J": "m", "K": 11194, "P": 81, "V": "97,534", "Y": 57, "S": 81}, {"D": "2:17:02", "I": "9gSlWDxIElE", "J": "m", "K": 11194, "P": 81, "V": "52,730", "Y": 57, "S": 81}, {"D": "2:17:26", "I": "FaARuovcIMM", "J": "m", "K": 11194, "P": 81, "V": "36,393", "Y": 57, "S": 81}, {"D": "2:17:33", "I": "ENN1ey9LpDQ", "J": "m", "K": 11194, "P": 81, "V": "26,211", "Y": 57, "S": 81}, {"D": "2:01:53", "I": "XalxWNDRi9M", "J": "m", "K": 11194, "P": 81, "V": "4,935", "Y": 57, "S": 81}, {"D": "2:17:34", "I": "lbVf1n1Ynok", "J": "m", "K": 11194, "P": 81, "V": "4,279", "Y": 57, "S": 81}, {"D": "2:17:33", "I": "-YlsL69tgoI", "J": "m", "K": 11194, "P": 81, "V": "2,687", "Y": 57, "S": 81}, {"D": "2:21:42", "I": "wvzCHAcJMno", "J": "m", "K": 11194, "P": 81, "V": "2,114", "Y": 57, "S": 81}, {"D": "2:17:34", "I": "IVG-njg2VJ8", "J": "m", "K": 11194, "P": 81, "V": "1,290", "Y": 57, "S": 81}, {"D": "2:23:20", "I": "ut066EOdAEE", "J": "m", "K": 11194, "P": 81, "V": "724", "Y": 57, "S": 81}]}, {"M": 5749, "S": 909, "movies": [{"D": "2:32:13", "I": "bwwm14rJILc", "J": "m", "K": 1566, "P": 81, "V": "267,207", "Y": 65, "S": 909}, {"D": "2:32:13", "I": "87zQlTUO5kQ", "J": "m", "K": 1566, "P": 81, "V": "12,756", "Y": 65, "S": 909}, {"D": "1:39:29", "I": "W34WjPMFbWo", "J": "m", "K": 1566, "P": 81, "V": "6,381", "Y": 65, "S": 909}]}, {"M": 4310, "S": 268, "movies": [{"D": "2:25:07", "I": "CVohNSA4mDc", "J": "m", "K": 814, "P": 81, "V": "33,275", "Y": 55, "S": 268}, {"D": "2:25:18", "I": "-N4KCuDZQyE", "J": "m", "K": 814, "P": 81, "V": "28,574", "Y": 55, "S": 268}, {"D": "2:25:07", "I": "JApatvDFPHQ", "J": "m", "K": 814, "P": 81, "V": "1,658", "Y": 55, "S": 268}]}, {"M": 3920, "S": 343, "movies": [{"D": "2:22:17", "I": "lmHyvxzGx5E", "J": "m", "K": 1111, "P": 81, "V": "21,199", "Y": 53, "S": 343}, {"D": "2:21:03", "I": "bT4z9obkDNo", "J": "m", "K": 1111, "P": 81, "V": "17,405", "Y": 53, "S": 343}, {"D": "2:30:46", "I": "uNpy_53zhKU", "J": "m", "K": 1111, "P": 81, "V": "1,201", "Y": 53, "S": 343}]}, {"M": 3343, "S": 209, "movies": [{"D": "2:26:27", "I": "jPceISkWvR4", "J": "s", "K": 1111, "P": 81, "V": "1,572,198", "Y": 60, "S": 209}, {"D": "2:48:46", "I": "EHvS_UHvtCk", "J": "h", "K": 1111, "P": 81, "V": "1,408,133", "Y": 60, "S": 209}, {"D": "2:26:29", "I": "98yATx1AaFg", "J": "m", "K": 1111, "P": 81, "V": "1,387,059", "Y": 60, "S": 209}, {"D": "2:26:27", "I": "ew8w3-15T_g", "J": "m", "K": 1111, "P": 81, "V": "439,446", "Y": 60, "S": 209}, {"D": "2:26:54", "I": "VkOEvch3CgA", "J": "m", "K": 1111, "P": 81, "V": "48,596", "Y": 60, "S": 209}, {"D": "2:26:27", "I": "51oB0HzYuN8", "J": "m", "K": 1111, "P": 81, "V": "48,160", "Y": 60, "S": 209}, {"D": "2:26:27", "I": "__jNOf20bYQ", "J": "m", "K": 1111, "P": 81, "V": "1,439", "Y": 60, "S": 209}]}, {"M": 3291, "S": 81, "movies": [{"D": "2:42:46", "I": "0UdX3gkqXTw", "J": "m", "K": 730, "P": 81, "V": "244,080", "Y": 61, "S": 81}, {"D": "2:37:20", "I": "qF269zCOSuM", "J": "m", "K": 730, "P": 81, "V": "229,286", "Y": 61, "S": 81}, {"D": "2:49:24", "I": "RoqkN2zY69M", "J": "m", "K": 730, "P": 81, "V": "27,232", "Y": 61, "S": 81}, {"D": "2:36:22", "I": "sP6NegWoysk", "J": "m", "K": 730, "P": 81, "V": "26,722", "Y": 61, "S": 81}, {"D": "2:36:22", "I": "q08aFsog3ms", "J": "m", "K": 730, "P": 81, "V": "15,495", "Y": 61, "S": 81}, {"D": "2:43:42", "I": "wOkCujsxLmE", "J": "m", "K": 730, "P": 81, "V": "897", "Y": 61, "S": 81}]}, {"M": 1011, "S": 141, "movies": [{"D": "2:22:44", "I": "RQp1NG6JVvo", "J": "m", "K": 286, "P": 81, "V": "1,132,342", "Y": 44, "S": 141}, {"D": "1:45:25", "I": "d5nT9VY94-Y", "J": "m", "K": 286, "P": 81, "V": "157,203", "Y": 44, "S": 141}, {"D": "1:45:25", "I": "Vf-i2QppSJc", "J": "m", "K": 286, "P": 81, "V": "102,943", "Y": 44, "S": 141}, {"D": "1:47:10", "I": "orv-ksRrRJM", "J": "m", "K": 286, "P": 81, "V": "64,690", "Y": 44, "S": 141}, {"D": "1:47:10", "I": "2otvUk4ENkc", "J": "m", "K": 286, "P": 81, "V": "20,605", "Y": 44, "S": 141}]}, {"M": 170, "S": 1719, "movies": [{"D": "2:30:45", "I": "zz4__Ectksw", "J": "m", "K": 1666, "P": 81, "V": "428,016", "Y": 64, "S": 1719}, {"D": "2:24:25", "I": "4WT4ZwmzS9E", "J": "m", "K": 1666, "P": 81, "V": "79,315", "Y": 64, "S": 1719}]}, {"M": 95, "S": 937, "movies": [{"D": "1:52:49", "I": "1n8ZSlBhPCI", "J": "m", "K": 4245, "P": 81, "V": "19,274", "Y": 61, "S": 937}, {"D": "1:57:50", "I": "Cl8iuu9H9ok", "J": "m", "K": 4245, "P": 81, "V": "3,569", "Y": 61, "S": 937}]}]}], "movies": [{"I": "Oy-3UHhFb3M", "M": 10013, "Y": 58, "P": 81, "K": 1590, "D": "2:13:35", "V": "4,185", "J": "m", "S": 1145}, {"I": "0PhS1knOSYI", "M": 10013, "Y": 58, "P": 81, "K": 1590, "D": "2:13:35", "V": "158,577", "J": "m", "S": 1145}, {"I": "rNlJt1Rdq4E", "M": 10013, "Y": 58, "P": 81, "K": 1590, "D": "2:13:35", "V": "17,971", "J": "m", "S": 1145}, {"I": "g8F7JIgZx5I", "M": 10013, "Y": 58, "P": 81, "K": 1590, "D": "2:13:33", "V": "1,462", "J": "m", "S": 1145}, {"I": "hVZJx5yZb30", "M": 10013, "Y": 58, "P": 81, "K": 1590, "D": "2:13:35", "V": "42,940", "J": "s", "S": 1145}, {"I": "iTr17tLjsxg", "M": 9973, "Y": 41, "P": 81, "K": 379, "D": "2:15:59", "V": "183", "J": "h", "S": 81}, {"I": "IA1oZFC4wPE", "M": 9696, "Y": 60, "P": 81, "K": 289, "D": "2:36:27", "V": "22,031", "J": "m", "S": 104}, {"I": "msnQ73uhyR0", "M": 9696, "Y": 60, "P": 81, "K": 289, "D": "2:36:27", "V": "4,123,063", "J": "m", "S": 104}, {"I": "laXAHhDCmGg", "M": 9696, "Y": 60, "P": 81, "K": 289, "D": "2:36:31", "V": "6,485", "J": "m", "S": 104}, {"I": "TYFXnWq_X6o", "M": 9696, "Y": 60, "P": 81, "K": 289, "D": "2:36:41", "V": "7,867", "J": "h", "S": 104}, {"I": "P2480tncaec", "M": 9696, "Y": 60, "P": 81, "K": 289, "D": "2:36:32", "V": "5,051", "J": "m", "S": 104}, {"I": "6rg8Hc-8HgQ", "M": 9696, "Y": 60, "P": 81, "K": 289, "D": "2:36:38", "V": "4,041", "J": "m", "S": 104}, {"I": "5cATeVPJ-ko", "M": 9696, "Y": 60, "P": 81, "K": 289, "D": "2:36:31", "V": "26,622", "J": "m", "S": 104}, {"I": "Zh6-hVxHMAw", "M": 9696, "Y": 60, "P": 81, "K": 289, "D": "2:36:31", "V": "3,670", "J": "m", "S": 104}, {"I": "HujdhyUcfrw", "M": 9696, "Y": 60, "P": 81, "K": 289, "D": "2:36:27", "V": "3,417,512", "J": "m", "S": 104}, {"I": "Tcrb0AcXXQs", "M": 9120, "Y": 57, "P": 81, "K": 9495, "D": "1:20:36", "V": "15,455", "J": "m", "S": 75}, {"I": "xTFqWiSz7JE", "M": 9120, "Y": 57, "P": 81, "K": 9495, "D": "2:20:46", "V": "37,487", "J": "m", "S": 75}, {"I": "sDli08ZYGrg", "M": 9120, "Y": 57, "P": 81, "K": 9495, "D": "2:20:46", "V": "5,808", "J": "m", "S": 75}, {"I": "Qz3U4VhQWaU", "M": 9120, "Y": 57, "P": 81, "K": 9495, "D": "2:17:40", "V": "106,139", "J": "m", "S": 75}, {"I": "JMGlgGty4Nk", "M": 8951, "Y": 53, "P": 81, "K": 1990, "D": "2:10:06", "V": "9,479", "J": "m", "S": 84}, {"I": "1JHEUITaCjo", "M": 8951, "Y": 53, "P": 81, "K": 1990, "D": "2:10:05", "V": "11,315", "J": "m", "S": 84}, {"I": "bP-nkePPxG0", "M": 8951, "Y": 53, "P": 81, "K": 1990, "D": "2:10:19", "V": "16,477", "J": "h", "S": 84}, {"I": "PPW9KcyrATk", "M": 8299, "Y": 66, "P": 81, "K": 81, "D": "2:10:02", "V": "79,254", "J": "h", "S": 345}, {"I": "o8iZW-FSIBM", "M": 7902, "Y": 56, "P": 81, "K": 730, "D": "2:06:47", "V": "3,780,159", "J": "m", "S": 1430}, {"I": "5vTH16nAXhY", "M": 7902, "Y": 56, "P": 81, "K": 730, "D": "2:35:25", "V": "6,871,315", "J": "m", "S": 1430}, {"I": "aEaC5HKh6Pk", "M": 7902, "Y": 56, "P": 81, "K": 730, "D": "2:47:50", "V": "11,125", "J": "m", "S": 1430}, {"I": "t7P_xqKfjUA", "M": 7902, "Y": 56, "P": 81, "K": 730, "D": "2:35:01", "V": "221,955", "J": "m", "S": 1430}, {"I": "7fu4t-wkH_Y", "M": 7902, "Y": 56, "P": 81, "K": 730, "D": "2:47:51", "V": "7,861", "J": "m", "S": 1430}, {"I": "dHdcQMu4Jw4", "M": 7902, "Y": 56, "P": 81, "K": 730, "D": "2:47:50", "V": "4,190", "J": "m", "S": 1430}, {"I": "EPhXAbc3ZmE", "M": 7902, "Y": 56, "P": 81, "K": 730, "D": "2:48:01", "V": "565,321", "J": "m", "S": 1430}, {"I": "5V_OgEwAADE", "M": 7902, "Y": 56, "P": 81, "K": 730, "D": "2:47:50", "V": "2,458", "J": "m", "S": 1430}, {"I": "YTForPxFZZY", "M": 7902, "Y": 56, "P": 81, "K": 730, "D": "2:41:35", "V": "2,148", "J": "m", "S": 1430}, {"I": "PqTcJncAE5c", "M": 7902, "Y": 56, "P": 81, "K": 730, "D": "2:35:17", "V": "19,324", "J": "m", "S": 1430}, {"I": "BwcojKDfUWU", "M": 7666, "Y": 41, "P": 81, "K": 153, "D": "1:57:34", "V": "23,834", "J": "m", "S": 249}, {"I": "cVQ1Ju7hcA0", "M": 7361, "Y": 54, "P": 81, "K": 752, "D": "2:26:27", "V": "10,866", "J": "m", "S": 861}, {"I": "ouI6ZRnQp0M", "M": 7361, "Y": 54, "P": 81, "K": 752, "D": "3:09:21", "V": "22,967", "J": "m", "S": 861}, {"I": "bQWdbamfpjA", "M": 7361, "Y": 54, "P": 81, "K": 752, "D": "2:20:39", "V": "8,219", "J": "h", "S": 861}, {"I": "UA57T609gJo", "M": 7282, "Y": 50, "P": 81, "K": 752, "D": "2:49:14", "V": "18,727", "J": "m", "S": 861}, {"I": "IbDZfKxLJFU", "M": 7282, "Y": 50, "P": 81, "K": 752, "D": "2:49:14", "V": "3,420", "J": "m", "S": 861}, {"I": "jqrmngTnlHA", "M": 7282, "Y": 50, "P": 81, "K": 752, "D": "2:34:42", "V": "3,144", "J": "m", "S": 861}, {"I": "Glc_2cEusdQ", "M": 6645, "Y": 51, "P": 81, "K": 257, "D": "1:45:58", "V": "16,937", "J": "h", "S": 104}, {"I": "laSuILUGnGw", "M": 6645, "Y": 51, "P": 81, "K": 257, "D": "1:45:40", "V": "42,842", "J": "m", "S": 104}, {"I": "9gSlWDxIElE", "M": 5993, "Y": 57, "P": 81, "K": 11194, "D": "2:17:02", "V": "52,730", "J": "m", "S": 81}, {"I": "rPy0W3SAXrc", "M": 5993, "Y": 57, "P": 81, "K": 11194, "D": "2:17:34", "V": "456,146", "J": "m", "S": 81}, {"I": "-YlsL69tgoI", "M": 5993, "Y": 57, "P": 81, "K": 11194, "D": "2:17:33", "V": "2,687", "J": "m", "S": 81}, {"I": "zuLU9bRsTJI", "M": 5993, "Y": 57, "P": 81, "K": 11194, "D": "2:17:33", "V": "117,154", "J": "m", "S": 81}, {"I": "ut066EOdAEE", "M": 5993, "Y": 57, "P": 81, "K": 11194, "D": "2:23:20", "V": "724", "J": "m", "S": 81}, {"I": "lbVf1n1Ynok", "M": 5993, "Y": 57, "P": 81, "K": 11194, "D": "2:17:34", "V": "4,279", "J": "m", "S": 81}, {"I": "FaARuovcIMM", "M": 5993, "Y": 57, "P": 81, "K": 11194, "D": "2:17:26", "V": "36,393", "J": "m", "S": 81}, {"I": "gmXcIa1qlTs", "M": 5993, "Y": 57, "P": 81, "K": 11194, "D": "2:17:31", "V": "97,534", "J": "m", "S": 81}, {"I": "0lUyhaSQMzU", "M": 5993, "Y": 57, "P": 81, "K": 11194, "D": "2:23:20", "V": "102,969", "J": "m", "S": 81}, {"I": "ENN1ey9LpDQ", "M": 5993, "Y": 57, "P": 81, "K": 11194, "D": "2:17:33", "V": "26,211", "J": "m", "S": 81}, {"I": "IVG-njg2VJ8", "M": 5993, "Y": 57, "P": 81, "K": 11194, "D": "2:17:34", "V": "1,290", "J": "m", "S": 81}, {"I": "wvzCHAcJMno", "M": 5993, "Y": 57, "P": 81, "K": 11194, "D": "2:21:42", "V": "2,114", "J": "m", "S": 81}, {"I": "XalxWNDRi9M", "M": 5993, "Y": 57, "P": 81, "K": 11194, "D": "2:01:53", "V": "4,935", "J": "m", "S": 81}, {"I": "72qLogUlJRQ", "M": 5993, "Y": 57, "P": 81, "K": 11194, "D": "2:17:34", "V": "1,927,990", "J": "m", "S": 81}, {"I": "bwwm14rJILc", "M": 5749, "Y": 65, "P": 81, "K": 1566, "D": "2:32:13", "V": "267,207", "J": "m", "S": 909}, {"I": "87zQlTUO5kQ", "M": 5749, "Y": 65, "P": 81, "K": 1566, "D": "2:32:13", "V": "12,756", "J": "m", "S": 909}, {"I": "W34WjPMFbWo", "M": 5749, "Y": 65, "P": 81, "K": 1566, "D": "1:39:29", "V": "6,381", "J": "m", "S": 909}, {"I": "CVohNSA4mDc", "M": 4310, "Y": 55, "P": 81, "K": 814, "D": "2:25:07", "V": "33,275", "J": "m", "S": 268}, {"I": "JApatvDFPHQ", "M": 4310, "Y": 55, "P": 81, "K": 814, "D": "2:25:07", "V": "1,658", "J": "m", "S": 268}, {"I": "-N4KCuDZQyE", "M": 4310, "Y": 55, "P": 81, "K": 814, "D": "2:25:18", "V": "28,574", "J": "m", "S": 268}, {"I": "bT4z9obkDNo", "M": 3920, "Y": 53, "P": 81, "K": 1111, "D": "2:21:03", "V": "17,405", "J": "m", "S": 343}, {"I": "lmHyvxzGx5E", "M": 3920, "Y": 53, "P": 81, "K": 1111, "D": "2:22:17", "V": "21,199", "J": "m", "S": 343}, {"I": "uNpy_53zhKU", "M": 3920, "Y": 53, "P": 81, "K": 1111, "D": "2:30:46", "V": "1,201", "J": "m", "S": 343}, {"I": "51oB0HzYuN8", "M": 3343, "Y": 60, "P": 81, "K": 1111, "D": "2:26:27", "V": "48,160", "J": "m", "S": 209}, {"I": "EHvS_UHvtCk", "M": 3343, "Y": 60, "P": 81, "K": 1111, "D": "2:48:46", "V": "1,408,133", "J": "h", "S": 209}, {"I": "98yATx1AaFg", "M": 3343, "Y": 60, "P": 81, "K": 1111, "D": "2:26:29", "V": "1,387,059", "J": "m", "S": 209}, {"I": "__jNOf20bYQ", "M": 3343, "Y": 60, "P": 81, "K": 1111, "D": "2:26:27", "V": "1,439", "J": "m", "S": 209}, {"I": "VkOEvch3CgA", "M": 3343, "Y": 60, "P": 81, "K": 1111, "D": "2:26:54", "V": "48,596", "J": "m", "S": 209}, {"I": "jPceISkWvR4", "M": 3343, "Y": 60, "P": 81, "K": 1111, "D": "2:26:27", "V": "1,572,198", "J": "s", "S": 209}, {"I": "ew8w3-15T_g", "M": 3343, "Y": 60, "P": 81, "K": 1111, "D": "2:26:27", "V": "439,446", "J": "m", "S": 209}, {"I": "qF269zCOSuM", "M": 3291, "Y": 61, "P": 81, "K": 730, "D": "2:37:20", "V": "229,286", "J": "m", "S": 81}, {"I": "sP6NegWoysk", "M": 3291, "Y": 61, "P": 81, "K": 730, "D": "2:36:22", "V": "26,722", "J": "m", "S": 81}, {"I": "0UdX3gkqXTw", "M": 3291, "Y": 61, "P": 81, "K": 730, "D": "2:42:46", "V": "244,080", "J": "m", "S": 81}, {"I": "q08aFsog3ms", "M": 3291, "Y": 61, "P": 81, "K": 730, "D": "2:36:22", "V": "15,495", "J": "m", "S": 81}, {"I": "RoqkN2zY69M", "M": 3291, "Y": 61, "P": 81, "K": 730, "D": "2:49:24", "V": "27,232", "J": "m", "S": 81}, {"I": "wOkCujsxLmE", "M": 3291, "Y": 61, "P": 81, "K": 730, "D": "2:43:42", "V": "897", "J": "m", "S": 81}, {"I": "2otvUk4ENkc", "M": 1011, "Y": 44, "P": 81, "K": 286, "D": "1:47:10", "V": "20,605", "J": "m", "S": 141}, {"I": "d5nT9VY94-Y", "M": 1011, "Y": 44, "P": 81, "K": 286, "D": "1:45:25", "V": "157,203", "J": "m", "S": 141}, {"I": "orv-ksRrRJM", "M": 1011, "Y": 44, "P": 81, "K": 286, "D": "1:47:10", "V": "64,690", "J": "m", "S": 141}, {"I": "RQp1NG6JVvo", "M": 1011, "Y": 44, "P": 81, "K": 286, "D": "2:22:44", "V": "1,132,342", "J": "m", "S": 141}, {"I": "Vf-i2QppSJc", "M": 1011, "Y": 44, "P": 81, "K": 286, "D": "1:45:25", "V": "102,943", "J": "m", "S": 141}, {"I": "zz4__Ectksw", "M": 170, "Y": 64, "P": 81, "K": 1666, "D": "2:30:45", "V": "428,016", "J": "m", "S": 1719}, {"I": "4WT4ZwmzS9E", "M": 170, "Y": 64, "P": 81, "K": 1666, "D": "2:24:25", "V": "79,315", "J": "m", "S": 1719}, {"I": "1n8ZSlBhPCI", "M": 95, "Y": 61, "P": 81, "K": 4245, "D": "1:52:49", "V": "19,274", "J": "m", "S": 937}, {"I": "Cl8iuu9H9ok", "M": 95, "Y": 61, "P": 81, "K": 4245, "D": "1:57:50", "V": "3,569", "J": "m", "S": 937}], "folders": [["movie", 10013, "0,1,2,3,4"], ["movie", 9973, "5"], ["movie", 9696, "6,7,8,9,10,11,12,13,14"], ["movie", 9120, "15,16,17,18"], ["movie", 8951, "19,20,21"], ["movie", 8299, "22"], ["movie", 7902, "23,24,25,26,27,28,29,30,31,32"], ["movie", 7666, "33"], ["movie", 7361, "34,35,36"], ["movie", 7282, "37,38,39"], ["movie", 6645, "40,41"], ["movie", 5993, "42,43,44,45,46,47,48,49,50,51,52,53,54,55"], ["movie", 5749, "56,57,58"], ["movie", 4310, "59,60,61"], ["movie", 3920, "62,63,64"], ["movie", 3343, "65,66,67,68,69,70,71"], ["movie", 3291, "72,73,74,75,76,77"], ["movie", 1011, "78,79,80,81,82"], ["movie", 170, "83,84"], ["movie", 95, "85,86"]], "languages": {"english": "0,1,2,3,4,5,6,7,8,9,10,11,12,13,14,15,16,17,18,19", "tamil": "1,2,0,9,8,5,11,19,12,17,7,6,3,16,4,15,13,14,18,10", "telugu": "1,2,0,9,8,5,11,19,12,17,7,6,16,15,3,4,13,14,18,10", "kannada": "1,2,0,9,8,5,11,19,12,17,7,6,16,15,3,4,13,14,18,10", "malayalam": "1,2,0,9,8,5,11,19,12,17,7,6,16,15,3,4,13,14,18,10", "hindi": "1,2,0,9,8,5,11,12,17,7,6,16,15,3,4,13,14,18,10,19", "marathi": "1,2,0,9,8,5,11,12,17,7,6,16,15,3,4,13,14,18,10,19", "bengali": "1,2,0,9,8,5,11,19,12,17,7,6,16,15,3,4,13,14,18,10", "gujarati": "1,2,0,9,8,5,11,19,12,17,7,6,16,15,3,4,13,14,18,10", "punjabi": "1,2,0,9,8,5,11,19,12,17,7,6,16,15,3,4,13,14,18,10", "odia": "1,2,0,9,8,5,11,19,12,17,7,6,16,15,3,4,13,14,18,10", "assamese": "1,2,0,9,8,5,11,19,12,17,7,6,16,15,3,4,13,14,18,10"}}