{"stats": [{"H": "Videos", "C": "14"}, {"H": "Movies", "C": "6"}, {"H": "Years", "C": "3"}, {"H": "Duration", "C": "32 H"}, {"H": "Views", "C": "18 M"}], "poster": {"P": "Images/person.jpg"}, "title": {"H": "Ranjeeta", "V": "ranjeeta", "I": "person-fill"}, "videos": [{"folder": [{"M": 8822, "S": 1213, "movies": [{"D": "2:42:22", "I": "xPPVJhmyR_I", "J": "m", "K": 2160, "P": 1213, "V": "13,103,620", "Y": 80, "S": 1213}, {"D": "2:17:00", "I": "YNIYznS0zDs", "J": "m", "K": 2160, "P": 1213, "V": "435,860", "Y": 80, "S": 1213}, {"D": "2:19:24", "I": "z5hWwAIxo3M", "J": "m", "K": 2160, "P": 1213, "V": "217,734", "Y": 80, "S": 1213}, {"D": "1:51:32", "I": "8K0WZKqGXuc", "J": "m", "K": 2160, "P": 1213, "V": "199,177", "Y": 80, "S": 1213}, {"D": "2:14:33", "I": "rMkT8YBnDBY", "J": "m", "K": 2160, "P": 1213, "V": "12,391", "Y": 80, "S": 1213}, {"D": "1:47:21", "I": "DJnhb2aBUMM", "J": "m", "K": 2160, "P": 1213, "V": "1,282", "Y": 80, "S": 1213}]}, {"M": 8084, "S": 1213, "movies": [{"D": "1:50:29", "I": "OwUbtxB2yhg", "J": "m", "K": 1474, "P": 1213, "V": "511,672", "Y": 79, "S": 1213}]}, {"M": 7797, "S": 546, "movies": [{"D": "2:32:35", "I": "9go_PyGd8oQ", "J": "m", "K": 770, "P": 1213, "V": "74,311", "Y": 82, "S": 546}, {"D": "2:32:35", "I": "F1vo7UGR-XE", "J": "m", "K": 770, "P": 1213, "V": "71,655", "Y": 82, "S": 546}, {"D": "2:00:51", "I": "jLZsYYKqEbk", "J": "m", "K": 770, "P": 1213, "V": "41,395", "Y": 82, "S": 546}, {"D": "2:32:35", "I": "xZN3AsdD35I", "J": "s", "K": 770, "P": 1213, "V": "33", "Y": 82, "S": 546}]}, {"M": 6322, "S": 2, "movies": [{"D": "2:35:43", "I": "nPwHvzoaaRA", "J": "m", "K": 772, "P": 1213, "V": "1,115,325", "Y": 82, "S": 2}]}, {"M": 5731, "S": 1213, "movies": [{"D": "2:40:54", "I": "OjwUjpOy_vc", "J": "m", "K": 2853, "P": 1213, "V": "1,881,868", "Y": 82, "S": 1213}]}, {"M": 3732, "S": 1213, "movies": [{"D": "2:09:46", "I": "daX8d9w8yXQ", "J": "m", "K": 3550, "P": 1213, "V": "28,419", "Y": 82, "S": 1213}]}]}], "movies": [{"I": "xPPVJhmyR_I", "M": 8822, "Y": 80, "P": 1213, "K": 2160, "D": "2:42:22", "V": "13,103,620", "J": "m", "S": 1213}, {"I": "YNIYznS0zDs", "M": 8822, "Y": 80, "P": 1213, "K": 2160, "D": "2:17:00", "V": "435,860", "J": "m", "S": 1213}, {"I": "z5hWwAIxo3M", "M": 8822, "Y": 80, "P": 1213, "K": 2160, "D": "2:19:24", "V": "217,734", "J": "m", "S": 1213}, {"I": "8K0WZKqGXuc", "M": 8822, "Y": 80, "P": 1213, "K": 2160, "D": "1:51:32", "V": "199,177", "J": "m", "S": 1213}, {"I": "rMkT8YBnDBY", "M": 8822, "Y": 80, "P": 1213, "K": 2160, "D": "2:14:33", "V": "12,391", "J": "m", "S": 1213}, {"I": "DJnhb2aBUMM", "M": 8822, "Y": 80, "P": 1213, "K": 2160, "D": "1:47:21", "V": "1,282", "J": "m", "S": 1213}, {"I": "OwUbtxB2yhg", "M": 8084, "Y": 79, "P": 1213, "K": 1474, "D": "1:50:29", "V": "511,672", "J": "m", "S": 1213}, {"I": "9go_PyGd8oQ", "M": 7797, "Y": 82, "P": 1213, "K": 770, "D": "2:32:35", "V": "74,311", "J": "m", "S": 546}, {"I": "F1vo7UGR-XE", "M": 7797, "Y": 82, "P": 1213, "K": 770, "D": "2:32:35", "V": "71,655", "J": "m", "S": 546}, {"I": "jLZsYYKqEbk", "M": 7797, "Y": 82, "P": 1213, "K": 770, "D": "2:00:51", "V": "41,395", "J": "m", "S": 546}, {"I": "xZN3AsdD35I", "M": 7797, "Y": 82, "P": 1213, "K": 770, "D": "2:32:35", "V": "33", "J": "s", "S": 546}, {"I": "nPwHvzoaaRA", "M": 6322, "Y": 82, "P": 1213, "K": 772, "D": "2:35:43", "V": "1,115,325", "J": "m", "S": 2}, {"I": "OjwUjpOy_vc", "M": 5731, "Y": 82, "P": 1213, "K": 2853, "D": "2:40:54", "V": "1,881,868", "J": "m", "S": 1213}, {"I": "daX8d9w8yXQ", "M": 3732, "Y": 82, "P": 1213, "K": 3550, "D": "2:09:46", "V": "28,419", "J": "m", "S": 1213}], "folders": [["movie", 8822, "0,1,2,3,4,5"], ["movie", 8084, "6"], ["movie", 7797, "7,8,9,10"], ["movie", 6322, "11"], ["movie", 5731, "12"], ["movie", 3732, "13"]], "languages": {"english": "0,1,2,3,4,5", "tamil": "4,1,2,5,0,3", "telugu": "4,1,2,5,0,3", "kannada": "4,1,2,5,0,3", "malayalam": "4,1,2,5,0,3", "hindi": "4,1,2,5,0,3", "marathi": "4,1,2,5,0,3", "bengali": "4,1,2,5,0,3", "gujarati": "4,1,2,5,0,3", "punjabi": "4,1,2,5,0,3", "odia": "4,1,2,5,0,3", "assamese": "4,1,2,5,0,3"}}