{"stats": [{"H": "Videos", "C": "3"}, {"H": "Movies", "C": "1"}, {"H": "Years", "C": "1"}, {"H": "Duration", "C": "6 H"}, {"H": "Views", "C": "308 K"}], "poster": {"P": "Images/person.jpg"}, "title": {"H": "Slochana Sen", "V": "slochana sen", "I": "person-fill"}, "videos": [{"folder": [{"M": 3821, "S": 255, "movies": [{"D": "2:15:56", "I": "id8IZXjdOz4", "J": "m", "K": 289, "P": 5460, "V": "214,585", "Y": 58, "S": 255}, {"D": "2:15:56", "I": "V2eN6Apgxx8", "J": "m", "K": 289, "P": 5460, "V": "82,860", "Y": 58, "S": 255}, {"D": "2:15:56", "I": "l5hfEiPHgXs", "J": "m", "K": 289, "P": 5460, "V": "10,220", "Y": 58, "S": 255}]}]}]}