{"stats": [{"H": "Videos", "C": "48"}, {"H": "Movies", "C": "13"}, {"H": "Years", "C": "8"}, {"H": "Duration", "C": "102 H"}, {"H": "Views", "C": "19 M"}], "poster": {"P": "Images/person.jpg"}, "title": {"T": 704, "H": "Vidya Sinha", "V": "vidya sinhA", "I": "person-fill"}, "movies": [{"I": "0VA6mtNGMok", "M": 9448, "Y": 79, "P": 704, "K": 1585, "D": "2:17:52", "V": "164,472", "J": "m", "S": 48}, {"I": "OW7POueQa_g", "M": 9448, "Y": 79, "P": 704, "K": 1585, "D": "2:17:11", "V": "56,056", "J": "m", "S": 48}, {"I": "MkPs6zS-2xw", "M": 9448, "Y": 79, "P": 704, "K": 1585, "D": "2:17:50", "V": "10,577", "J": "m", "S": 48}, {"I": "U70AMFZEnJg", "M": 9448, "Y": 79, "P": 704, "K": 1585, "D": "2:17:50", "V": "10,313", "J": "m", "S": 48}, {"I": "pKZmW06Dmcs", "M": 9448, "Y": 79, "P": 704, "K": 1585, "D": "2:17:50", "V": "3,190", "J": "m", "S": 48}, {"I": "BZl11NabjOU", "M": 9448, "Y": 79, "P": 704, "K": 1585, "D": "2:23:43", "V": "2,802", "J": "m", "S": 48}, {"I": "S08wLJnbpsw", "M": 8295, "Y": 77, "P": 704, "K": 420, "D": "1:59:13", "V": "1,842,770", "J": "m", "S": 704}, {"I": "HViOdHd90Aw", "M": 8295, "Y": 77, "P": 704, "K": 420, "D": "1:59:12", "V": "509,537", "J": "m", "S": 704}, {"I": "I4x7d1Z_azM", "M": 5696, "Y": 82, "P": 704, "K": 598, "D": "2:00:27", "V": "175,760", "J": "h", "S": 258}, {"I": "Cm50JVcn3yc", "M": 5696, "Y": 82, "P": 704, "K": 598, "D": "2:00:32", "V": "172,415", "J": "m", "S": 258}, {"I": "4fPEoiswqS4", "M": 5696, "Y": 82, "P": 704, "K": 598, "D": "2:01:02", "V": "149,972", "J": "m", "S": 258}, {"I": "9jAFiSsgbe8", "M": 5696, "Y": 82, "P": 704, "K": 598, "D": "2:00:49", "V": "6,218", "J": "m", "S": 258}, {"I": "azGbRGoEIrQ", "M": 5386, "Y": 78, "P": 704, "K": 821, "D": "2:26:19", "V": "1,186,789", "J": "m", "S": 704}, {"I": "X2n5MX6qKX4", "M": 5386, "Y": 78, "P": 704, "K": 821, "D": "2:13:51", "V": "5,811", "J": "m", "S": 704}, {"I": "P9gobjGHzkA", "M": 4556, "Y": 80, "P": 704, "K": 1386, "D": "2:16:32", "V": "101,769", "J": "m", "S": 704}, {"I": "gDUbOKHJ70k", "M": 4228, "Y": 80, "P": 704, "K": 208, "D": "2:19:26", "V": "4,841,768", "J": "m", "S": 29}, {"I": "UlPQOLJXzj4", "M": 4228, "Y": 80, "P": 704, "K": 208, "D": "1:46:54", "V": "826,727", "J": "m", "S": 29}, {"I": "3G9hdrOPMiI", "M": 4228, "Y": 80, "P": 704, "K": 208, "D": "2:19:43", "V": "792,083", "J": "m", "S": 29}, {"I": "wKtPbD_IoMg", "M": 4228, "Y": 80, "P": 704, "K": 208, "D": "2:14:30", "V": "396,992", "J": "m", "S": 29}, {"I": "DMEoPDvnWds", "M": 4228, "Y": 80, "P": 704, "K": 208, "D": "1:46:54", "V": "218,449", "J": "m", "S": 29}, {"I": "RaFCYx0Lhac", "M": 4228, "Y": 80, "P": 704, "K": 208, "D": "2:16:00", "V": "147,331", "J": "m", "S": 29}, {"I": "QQlkQvHZGXQ", "M": 4228, "Y": 80, "P": 704, "K": 208, "D": "2:20:08", "V": "51,292", "J": "s", "S": 29}, {"I": "o3wTrWHoUCM", "M": 4228, "Y": 80, "P": 704, "K": 208, "D": "1:49:31", "V": "40,331", "J": "m", "S": 29}, {"I": "fQ2AyEq5pKI", "M": 4228, "Y": 80, "P": 704, "K": 208, "D": "1:46:54", "V": "22,684", "J": "m", "S": 29}, {"I": "vN8THgUwHQY", "M": 4228, "Y": 80, "P": 704, "K": 208, "D": "1:46:54", "V": "3,944", "J": "m", "S": 29}, {"I": "LrstPFQoFu0", "M": 4228, "Y": 80, "P": 704, "K": 208, "D": "1:49:31", "V": "2,149", "J": "m", "S": 29}, {"I": "-N8_YzBBWmo", "M": 3881, "Y": 78, "P": 704, "K": 2683, "D": "2:32:15", "V": "644,828", "J": "m", "S": 704}, {"I": "F8R7miwfTaI", "M": 3881, "Y": 78, "P": 704, "K": 2683, "D": "2:31:36", "V": "83,096", "J": "m", "S": 704}, {"I": "UWOKE7tQFZQ", "M": 3881, "Y": 78, "P": 704, "K": 2683, "D": "2:32:00", "V": "12,949", "J": "m", "S": 704}, {"I": "ZtX2nBjWUHM", "M": 3186, "Y": 79, "P": 704, "K": 821, "D": "2:10:11", "V": "442,426", "J": "m", "S": 704}, {"I": "5OTg9QtUoB0", "M": 3186, "Y": 79, "P": 704, "K": 821, "D": "2:05:50", "V": "237,290", "J": "s", "S": 704}, {"I": "hb2pdPDO7DM", "M": 2589, "Y": 75, "P": 704, "K": 420, "D": "1:43:40", "V": "818,593", "J": "m", "S": 704}, {"I": "iTMbCPaVaoo", "M": 2589, "Y": 75, "P": 704, "K": 420, "D": "1:43:40", "V": "562,428", "J": "m", "S": 704}, {"I": "vf_xkizJb90", "M": 2589, "Y": 75, "P": 704, "K": 420, "D": "1:43:02", "V": "13,433", "J": "m", "S": 704}, {"I": "uvTNo0UjlN0", "M": 2736, "Y": 83, "P": 704, "K": 2160, "D": "1:56:56", "V": "335,536", "J": "m", "S": 512}, {"I": "X59eitW7quE", "M": 2736, "Y": 83, "P": 704, "K": 2160, "D": "1:56:56", "V": "21,267", "J": "m", "S": 512}, {"I": "qwbplAADzG0", "M": 2208, "Y": 81, "P": 704, "K": 677, "D": "2:12:22", "V": "1,141,645", "J": "m", "S": 704}, {"I": "Sd1gGXjAS7g", "M": 2208, "Y": 81, "P": 704, "K": 677, "D": "2:12:29", "V": "622,346", "J": "m", "S": 704}, {"I": "N3PV0rIySFw", "M": 2208, "Y": 81, "P": 704, "K": 677, "D": "2:06:03", "V": "180,884", "J": "m", "S": 704}, {"I": "bV9v4fFJjgM", "M": 2208, "Y": 81, "P": 704, "K": 677, "D": "2:23:14", "V": "107,541", "J": "m", "S": 704}, {"I": "2SBvOFZK0Eo", "M": 2208, "Y": 81, "P": 704, "K": 677, "D": "2:17:16", "V": "94,232", "J": "m", "S": 704}, {"I": "_XXgSzjANz8", "M": 2208, "Y": 81, "P": 704, "K": 677, "D": "2:05:25", "V": "29,750", "J": "m", "S": 704}, {"I": "_hF4yoxhwKI", "M": 2208, "Y": 81, "P": 704, "K": 677, "D": "2:05:25", "V": "7,637", "J": "m", "S": 704}, {"I": "rV5sQZ_oW5A", "M": 2208, "Y": 81, "P": 704, "K": 677, "D": "1:54:36", "V": "1,825", "J": "m", "S": 704}, {"I": "sXrVQt9VhXY", "M": 1301, "Y": 79, "P": 704, "K": 3749, "D": "2:06:35", "V": "841,796", "J": "m", "S": 74}, {"I": "RXMoAM5eNjs", "M": 1099, "Y": 81, "P": 704, "K": 3694, "D": "2:37:27", "V": "434,020", "J": "m", "S": 32}, {"I": "j2ZUs8jfcIs", "M": 1099, "Y": 81, "P": 704, "K": 3694, "D": "2:37:36", "V": "299,150", "J": "m", "S": 32}, {"I": "TNqiO7H6OEw", "M": 1099, "Y": 81, "P": 704, "K": 3694, "D": "2:37:27", "V": "11,743", "J": "m", "S": 32}], "folders": [["movie", 9448, "0,1,2,3,4,5"], ["movie", 8295, "6,7"], ["movie", 5696, "8,9,10,11"], ["movie", 5386, "12,13"], ["movie", 4556, "14"], ["movie", 4228, "15,16,17,18,19,20,21,22,23,24,25"], ["movie", 3881, "26,27,28"], ["movie", 3186, "29,30"], ["movie", 2589, "31,32,33"], ["movie", 2736, "34,35"], ["movie", 2208, "36,37,38,39,40,41,42,43"], ["movie", 1301, "44"], ["movie", 1099, "45,46,47"]], "languages": {"english": "0,1,2,3,4,5,6,7,9,8,10,11,12", "tamil": "0,3,10,11,1,2,7,4,5,6,8,9,12", "telugu": "0,3,1,2,7,4,5,6,8,9,10,11,12", "kannada": "0,3,1,2,7,4,5,6,8,9,10,11,12", "malayalam": "0,3,1,2,7,4,5,6,8,9,10,11,12", "hindi": "0,3,1,2,7,4,5,6,8,9,10,11,12", "marathi": "0,3,1,2,7,4,5,6,8,9,10,11,12", "bengali": "0,3,1,2,7,4,5,6,8,9,10,11,12", "gujarati": "0,3,1,2,7,4,5,6,8,9,10,11,12", "punjabi": "0,3,1,2,7,4,5,6,8,9,10,11,12", "odia": "0,3,1,2,7,4,5,6,8,9,10,11,12", "assamese": "0,3,1,2,7,4,5,6,8,9,10,11,12"}}