{"stats": [{"H": "Videos", "C": "1"}, {"H": "Years", "C": "1"}, {"H": "Persons", "C": "1"}, {"H": "Duration", "C": "2 H"}, {"H": "Views", "C": "124 K"}], "poster": {"P": "https://i.ytimg.com/vi/GUXsFf0yZPc/maxresdefault.jpg"}, "crew": [{"N": "Images/BISWA.jpg"}, {"N": "Images/REKHA.jpg"}, {"N": "Images/director.jpg"}], "title": {"T": 7651, "H": "Do Aankhen (1974)", "V": "dO A~khEM (1974)", "I": "film"}, "movies": [{"I": "GUXsFf0yZPc", "M": 7651, "Y": 75, "P": 366, "K": 4456, "D": "2:02:19", "V": "123,969", "J": "m", "S": 11}], "folders": [["year", 75, "0"]], "languages": {"english": "0", "tamil": "0", "telugu": "0", "kannada": "0", "malayalam": "0", "hindi": "0", "marathi": "0", "bengali": "0", "gujarati": "0", "punjabi": "0", "odia": "0", "assamese": "0"}}