{"stats": [{"H": "Videos", "C": "1"}, {"H": "Years", "C": "1"}, {"H": "Persons", "C": "1"}, {"H": "Duration", "C": "3 H"}, {"H": "Views", "C": "14 K"}], "poster": {"P": "https://i.ytimg.com/vi/eSPqFNABReg/maxresdefault.jpg"}, "crew": [{"N": "Images/person.jpg"}, {"N": "Images/person.jpg"}, {"N": "Images/director.jpg"}], "title": {"H": "Hatimtai Ki Beti (1955)", "V": "hatimtai ki beti (1955)", "I": "film"}, "videos": [{"folder": [{"Y": 56, "S": 213, "movies": [{"D": "3:10:16", "I": "eSPqFNABReg", "J": "m", "K": 92, "M": 6548, "P": 67, "V": "13,228", "S": 213}]}]}]}