{"stats": [{"H": "Videos", "C": "1"}, {"H": "Years", "C": "1"}, {"H": "Persons", "C": "1"}, {"H": "Duration", "C": "2 H"}, {"H": "Views", "C": "131 K"}], "poster": {"P": "https://i.ytimg.com/vi/9hjEa_6dWuk/maxresdefault.jpg"}, "crew": [{"N": "Images/GOVIND.jpg"}, {"N": "Images/NEELAM.jpg"}, {"N": "Images/director.jpg"}], "title": {"H": "Ilzaam (1986)", "V": "ilzaam (1986)", "I": "film"}, "videos": [{"folder": [{"Y": 87, "S": 284, "movies": [{"D": "2:26:37", "I": "9hjEa_6dWuk", "J": "m", "K": 471, "M": 6242, "P": 26, "V": "130,457", "S": 284}]}]}]}