{"stats": [{"H": "Videos", "C": "4"}, {"H": "Years", "C": "1"}, {"H": "Persons", "C": "1"}, {"H": "Duration", "C": "7 H"}, {"H": "Views", "C": "65 K"}], "poster": {"P": "https://i.ytimg.com/vi/9pH5I02ZETY/sddefault.jpg"}, "crew": [{"N": "Images/person.jpg"}, {"N": "Images/person.jpg"}, {"N": "Images/director.jpg"}], "title": {"T": 3464, "H": "Notebook (2019)", "V": "notebUk (2019)", "I": "film"}, "movies": [{"I": "9pH5I02ZETY", "M": 3464, "Y": 120, "P": 12272, "K": 2222, "D": "1:47:45", "V": "57,137", "J": "s", "S": 12060}, {"I": "N1SuDF2-VwA", "M": 3464, "Y": 120, "P": 12272, "K": 2222, "D": "1:46:49", "V": "5,352", "J": "s", "S": 12060}, {"I": "qJ2Ux2ShPOs", "M": 3464, "Y": 120, "P": 12272, "K": 2222, "D": "1:52:04", "V": "1,863", "J": "m", "S": 12060}, {"I": "CXME6uv4fpE", "M": 3464, "Y": 120, "P": 12272, "K": 2222, "D": "1:46:49", "V": "10", "J": "s", "S": 12060}], "folders": [["year", 120, "0,1,2,3"]], "languages": {"english": "0", "tamil": "0", "telugu": "0", "kannada": "0", "malayalam": "0", "hindi": "0", "marathi": "0", "bengali": "0", "gujarati": "0", "punjabi": "0", "odia": "0", "assamese": "0"}}