{"stats": [{"H": "Videos", "C": "3"}, {"H": "Years", "C": "1"}, {"H": "Persons", "C": "1"}, {"H": "Duration", "C": "6 H"}, {"H": "Views", "C": "6 M"}], "poster": {"P": "https://i.ytimg.com/vi/WrUnULAJ-bY/maxresdefault.jpg"}, "crew": [{"N": "Images/AKSHAY.jpg"}, {"N": "Images/person.jpg"}, {"N": "Images/director.jpg"}], "title": {"T": 144, "H": "Zaalim (1994)", "V": "zAlim (1994)", "I": "film"}, "movies": [{"I": "WrUnULAJ-bY", "M": 144, "Y": 95, "P": 36, "K": 1306, "D": "2:26:56", "V": "3,716,760", "J": "m", "S": 631}, {"I": "UZQd2kqoSqg", "M": 144, "Y": 95, "P": 36, "K": 1306, "D": "1:55:49", "V": "1,037,518", "J": "m", "S": 631}, {"I": "opSNZygMCIQ", "M": 144, "Y": 95, "P": 36, "K": 1306, "D": "2:28:57", "V": "477,739", "J": "m", "S": 631}], "folders": [["year", 95, "0,1,2"]], "languages": {"english": "0", "tamil": "0", "telugu": "0", "kannada": "0", "malayalam": "0", "hindi": "0", "marathi": "0", "bengali": "0", "gujarati": "0", "punjabi": "0", "odia": "0", "assamese": "0"}}