{"stats": [{"H": "Videos", "C": "1"}, {"H": "Years", "C": "1"}, {"H": "Persons", "C": "1"}, {"H": "Duration", "C": "2 H"}, {"H": "Views", "C": "78 K"}], "poster": {"P": "https://i.ytimg.com/vi/WwrtbM5JrpA/maxresdefault.jpg"}, "crew": [{"N": "Images/person.jpg"}, {"N": "Images/person.jpg"}, {"N": "Images/director.jpg"}], "title": {"T": 7099, "H": "Amara Kaaviyam (2014)", "V": "amara kAviyam (2014)", "I": "film"}, "movies": [{"I": "WwrtbM5JrpA", "M": 7099, "Y": 115, "P": 424, "K": 1819, "D": "2:26:15", "V": "77,641", "J": "m", "S": 995}], "folders": [["year", 115, "0"]], "languages": {"english": "0", "tamil": "0", "telugu": "0", "kannada": "0", "malayalam": "0", "hindi": "0", "marathi": "0", "bengali": "0", "gujarati": "0", "punjabi": "0", "odia": "0", "assamese": "0"}}