{"stats": [{"H": "Videos", "C": "11"}, {"H": "Years", "C": "1"}, {"H": "Persons", "C": "1"}, {"H": "Duration", "C": "24 H"}, {"H": "Views", "C": "2 M"}], "poster": {"P": "https://i.ytimg.com/vi/a6_9ttOkzDg/hqdefault.jpg"}, "crew": [{"N": "Images/RAJINI.jpg"}, {"N": "Images/person.jpg"}, {"N": "Images/RTRAJAN.jpg"}], "title": {"T": 3883, "H": "Anbukku Naan Adimai (1980)", "V": "anbukku nAn aDimai (1980)", "I": "film"}, "movies": [{"I": "a6_9ttOkzDg", "M": 3883, "Y": 81, "P": 28, "K": 309, "D": "2:09:40", "V": "513,001", "J": "h", "S": 365}, {"I": "DNXRsHF53Qs", "M": 3883, "Y": 81, "P": 28, "K": 309, "D": "2:11:35", "V": "320,706", "J": "s", "S": 365}, {"I": "QmmBMtAf3_w", "M": 3883, "Y": 81, "P": 28, "K": 309, "D": "2:09:26", "V": "77,569", "J": "m", "S": 365}, {"I": "u_RlSfWZJAY", "M": 3883, "Y": 81, "P": 28, "K": 309, "D": "2:09:41", "V": "66,141", "J": "m", "S": 365}, {"I": "e6AY1HrZbvo", "M": 3883, "Y": 81, "P": 28, "K": 309, "D": "2:17:14", "V": "48,132", "J": "m", "S": 365}, {"I": "NmJ6FhJ3dCs", "M": 3883, "Y": 81, "P": 28, "K": 309, "D": "2:09:25", "V": "23,961", "J": "m", "S": 365}, {"I": "TlSU-C63gM4", "M": 3883, "Y": 81, "P": 28, "K": 309, "D": "2:09:25", "V": "7,971", "J": "m", "S": 365}, {"I": "_ZmsPbOCKUY", "M": 3883, "Y": 81, "P": 28, "K": 309, "D": "2:17:47", "V": "4,998", "J": "m", "S": 365}, {"I": "n8B0ElnFjRk", "M": 3883, "Y": 81, "P": 28, "K": 309, "D": "2:12:48", "V": "1,514", "J": "m", "S": 365}, {"I": "uEq_inG1eiw", "M": 3883, "Y": 81, "P": 28, "K": 309, "D": "2:11:35", "V": "618", "J": "m", "S": 365}, {"I": "2V9iNpLxDMs", "M": 3883, "Y": 81, "P": 28, "K": 309, "D": "2:09:26", "V": "602", "J": "m", "S": 365}], "folders": [["year", 81, "0,1,2,3,4,5,6,7,8,9,10"]], "languages": {"english": "0", "tamil": "0", "telugu": "0", "kannada": "0", "malayalam": "0", "hindi": "0", "marathi": "0", "bengali": "0", "gujarati": "0", "punjabi": "0", "odia": "0", "assamese": "0"}}