{"stats": [{"H": "Videos", "C": "8"}, {"H": "Years", "C": "1"}, {"H": "Persons", "C": "1"}, {"H": "Duration", "C": "21 H"}, {"H": "Views", "C": "5 M"}], "poster": {"P": "https://i.ytimg.com/vi/t2T7NIB6FsE/maxresdefault.jpg"}, "crew": [{"N": "Images/MGR.jpg"}, {"N": "Images/JAYA.jpg"}, {"N": "Images/director.jpg"}], "title": {"T": 2333, "H": "Kudiyirundha Koyil (1968)", "V": "kuDiyiruMdha kOyil (1968)", "I": "film"}, "movies": [{"I": "t2T7NIB6FsE", "M": 2333, "Y": 69, "P": 20, "K": 122, "D": "2:34:25", "V": "2,015,339", "J": "m", "S": 51}, {"I": "CP82S60fGys", "M": 2333, "Y": 69, "P": 20, "K": 122, "D": "2:46:09", "V": "1,980,108", "J": "h", "S": 51}, {"I": "kMOFD8z_HCs", "M": 2333, "Y": 69, "P": 20, "K": 122, "D": "2:44:51", "V": "472,224", "J": "m", "S": 51}, {"I": "vpnPWmiPe6s", "M": 2333, "Y": 69, "P": 20, "K": 122, "D": "2:40:18", "V": "85,649", "J": "m", "S": 51}, {"I": "-sdSUtnZ9tE", "M": 2333, "Y": 69, "P": 20, "K": 122, "D": "2:43:58", "V": "38,166", "J": "m", "S": 51}, {"I": "v3qGm3LWG_E", "M": 2333, "Y": 69, "P": 20, "K": 122, "D": "2:25:13", "V": "27,788", "J": "m", "S": 51}, {"I": "xA93Fy-q_9Q", "M": 2333, "Y": 69, "P": 20, "K": 122, "D": "2:45:18", "V": "24,049", "J": "m", "S": 51}, {"I": "jl9zwqz9mt4", "M": 2333, "Y": 69, "P": 20, "K": 122, "D": "2:46:01", "V": "6,413", "J": "m", "S": 51}], "folders": [["year", 69, "0,1,2,3,4,5,6,7"]], "languages": {"english": "0", "tamil": "0", "telugu": "0", "kannada": "0", "malayalam": "0", "hindi": "0", "marathi": "0", "bengali": "0", "gujarati": "0", "punjabi": "0", "odia": "0", "assamese": "0"}}