{"stats": [{"H": "Videos", "C": "1"}, {"H": "Years", "C": "1"}, {"H": "Persons", "C": "1"}, {"H": "Duration", "C": "2 H"}, {"H": "Views", "C": "496 K"}], "poster": {"P": "https://i.ytimg.com/vi/8mItUqIsB_o/maxresdefault.jpg"}, "crew": [{"N": "Images/person.jpg"}, {"N": "Images/person.jpg"}, {"N": "Images/director.jpg"}], "title": {"H": "Pattanathil Petti (1990)", "V": "paTTaNatthil peTTi (1990)", "I": "film"}, "videos": [{"folder": [{"Y": 91, "S": 2211, "movies": [{"D": "2:07:51", "I": "8mItUqIsB_o", "J": "m", "K": 2388, "M": 785, "P": 2192, "V": "495,745", "S": 2211}]}]}]}