{"stats": [{"H": "Videos", "C": "4"}, {"H": "Years", "C": "1"}, {"H": "Persons", "C": "1"}, {"H": "Duration", "C": "10 H"}, {"H": "Views", "C": "640 K"}], "poster": {"P": "https://i.ytimg.com/vi/zlRcAoShBYw/maxresdefault.jpg"}, "crew": [{"N": "Images/RAJINI.jpg"}, {"N": "Images/KRV.jpg"}, {"N": "Images/SPM.jpg"}], "title": {"T": 3811, "H": "Sri Raghavendrar (1985)", "V": "SrI rAgavEMdirA (1985)", "I": "film"}, "movies": [{"I": "zlRcAoShBYw", "M": 3811, "Y": 86, "P": 28, "K": 71, "D": "2:33:29", "V": "610,662", "J": "m", "S": 14}, {"I": "mkCQ7Kv1MKI", "M": 3811, "Y": 86, "P": 28, "K": 71, "D": "2:33:28", "V": "13,826", "J": "m", "S": 14}, {"I": "CtAI49zrw1M", "M": 3811, "Y": 86, "P": 28, "K": 71, "D": "2:33:15", "V": "11,384", "J": "m", "S": 14}, {"I": "1Giil1DmU7g", "M": 3811, "Y": 86, "P": 28, "K": 71, "D": "2:33:07", "V": "3,615", "J": "h", "S": 14}], "folders": [["year", 86, "0,1,2,3"]], "languages": {"english": "0", "tamil": "0", "telugu": "0", "kannada": "0", "malayalam": "0", "hindi": "0", "marathi": "0", "bengali": "0", "gujarati": "0", "punjabi": "0", "odia": "0", "assamese": "0"}}