{"stats": [{"H": "Videos", "C": "16"}, {"H": "Movies", "C": "4"}, {"H": "Years", "C": "4"}, {"H": "Duration", "C": "37 H"}, {"H": "Views", "C": "11 M"}], "poster": {"P": "Images/director.jpg"}, "title": {"T": 2671, "H": "Rajesh Kumar Singh", "V": "rAjES kumAr singh", "I": "person-lines-fill"}, "movies": [{"I": "hVka8F0Vwfo", "M": 10005, "Y": 105, "P": 2132, "K": 2671, "D": "2:19:06", "V": "108,623", "J": "m", "S": 1112}, {"I": "rhxw9X0_4ZA", "M": 10110, "Y": 104, "P": 172, "K": 2671, "D": "2:25:08", "V": "2,996,989", "J": "h", "S": 61}, {"I": "iiLbDK8knNw", "M": 10110, "Y": 104, "P": 172, "K": 2671, "D": "2:25:08", "V": "70,448", "J": "m", "S": 61}, {"I": "g9ArOBvGFlA", "M": 10110, "Y": 104, "P": 172, "K": 2671, "D": "2:25:19", "V": "45,540", "J": "s", "S": 61}, {"I": "Frqqdn796b4", "M": 10110, "Y": 104, "P": 172, "K": 2671, "D": "2:25:08", "V": "20,735", "J": "s", "S": 61}, {"I": "M97kFh_W4gU", "M": 10110, "Y": 104, "P": 172, "K": 2671, "D": "2:25:08", "V": "1,246", "J": "h", "S": 61}, {"I": "svdNm_K5uKM", "M": 10110, "Y": 104, "P": 172, "K": 2671, "D": "2:25:08", "V": "647", "J": "h", "S": 61}, {"I": "0gnPO1aW5F8", "M": 10110, "Y": 104, "P": 172, "K": 2671, "D": "2:25:02", "V": "314", "J": "s", "S": 61}, {"I": "_OO9y8z_je4", "M": 10110, "Y": 104, "P": 172, "K": 2671, "D": "2:25:08", "V": "30", "J": "s", "S": 61}, {"I": "aWMs59tnE28", "M": 9356, "Y": 101, "P": 24, "K": 2671, "D": "2:42:09", "V": "5,791,542", "J": "m", "S": 157}, {"I": "myFriZBKklE", "M": 8949, "Y": 98, "P": 1001, "K": 2671, "D": "2:20:30", "V": "1,479,302", "J": "m", "S": 229}, {"I": "jM8VulYX1Bw", "M": 8949, "Y": 98, "P": 1001, "K": 2671, "D": "2:20:30", "V": "321,177", "J": "m", "S": 229}, {"I": "OidzJ5G3BcU", "M": 8949, "Y": 98, "P": 1001, "K": 2671, "D": "2:21:00", "V": "42,161", "J": "m", "S": 229}, {"I": "jfcviL_dG-8", "M": 8949, "Y": 98, "P": 1001, "K": 2671, "D": "2:20:33", "V": "8,026", "J": "h", "S": 229}, {"I": "Dc3SODhRgkc", "M": 8949, "Y": 98, "P": 1001, "K": 2671, "D": "2:14:06", "V": "2,244", "J": "h", "S": 229}, {"I": "1KgCVWTdgxs", "M": 8949, "Y": 98, "P": 1001, "K": 2671, "D": "1:53:39", "V": "18", "J": "s", "S": 229}], "folders": [["movie", 10005, "0"], ["movie", 10110, "1,2,3,4,5,6,7,8"], ["movie", 9356, "9"], ["movie", 8949, "10,11,12,13,14,15"]], "languages": {"english": "1,0,2,3", "tamil": "0,1,2,3", "telugu": "0,1,2,3", "kannada": "0,1,2,3", "malayalam": "0,1,2,3", "hindi": "0,1,2,3", "marathi": "0,1,2,3", "bengali": "0,1,2,3", "gujarati": "0,1,2,3", "punjabi": "0,1,2,3", "odia": "0,1,2,3", "assamese": "0,1,2,3"}}