{"stats": [{"H": "Videos", "C": "2"}, {"H": "Movies", "C": "2"}, {"H": "Years", "C": "2"}, {"H": "Duration", "C": "4 H"}, {"H": "Views", "C": "5 M"}], "poster": {"P": "Images/person.jpg"}, "title": {"H": "Misha Ghoshal", "V": "mishA ghOshAl", "I": "person-fill"}, "videos": [{"folder": [{"M": 6608, "movies": [{"D": "2:21:53", "I": "LAwsLmDr_LU", "J": "s", "K": 6687, "P": 5702, "V": "4,054,677", "Y": 117}]}, {"M": 3571, "movies": [{"D": "1:53:16", "I": "6G16A94y0nE", "J": "m", "K": 9031, "P": 5702, "V": "294,378", "Y": 116}]}]}]}