{"stats": [{"H": "Videos", "C": "14"}, {"H": "Movies", "C": "5"}, {"H": "Years", "C": "4"}, {"H": "Duration", "C": "32 H"}, {"H": "Views", "C": "39 M"}], "poster": {"P": "Images/person.jpg"}, "title": {"T": 758, "H": "Shruti Haasan", "V": "shruthi hAsan", "I": "person-fill"}, "movies": [{"I": "TrOYfZcfkjw", "M": 7230, "Y": 113, "P": 758, "K": 3049, "D": "1:29:34", "V": "84,518", "J": "m", "S": 758}, {"I": "QNhdeKRSVB0", "M": 7230, "Y": 113, "P": 758, "K": 3049, "D": "2:27:53", "V": "7", "J": "m", "S": 758}, {"I": "BzPzDI1IfJA", "M": 7220, "Y": 112, "P": 758, "K": 738, "D": "2:40:54", "V": "32,481,721", "J": "m", "S": 758}, {"I": "IB_h2APvIaQ", "M": 1875, "Y": 115, "P": 758, "K": 352, "D": "2:16:37", "V": "990,781", "J": "m", "S": 758}, {"I": "vR9K85uTaTY", "M": 1875, "Y": 115, "P": 758, "K": 352, "D": "2:16:37", "V": "472,070", "J": "m", "S": 758}, {"I": "hEj7g6sp4vw", "M": 1875, "Y": 115, "P": 758, "K": 352, "D": "2:20:26", "V": "18,133", "J": "h", "S": 758}, {"I": "Uy2mcoTLfeo", "M": 1875, "Y": 115, "P": 758, "K": 352, "D": "1:41:42", "V": "8,649", "J": "m", "S": 758}, {"I": "I7FlisC1AjE", "M": 5113, "Y": 116, "P": 758, "K": 1036, "D": "2:28:10", "V": "2,935,379", "J": "m", "S": 1566}, {"I": "IQ0bAJQmIi4", "M": 5113, "Y": 116, "P": 758, "K": 1036, "D": "2:47:39", "V": "15,804", "J": "m", "S": 1566}, {"I": "nqgQwsxeFYY", "M": 2156, "Y": 116, "P": 758, "K": 541, "D": "2:34:37", "V": "1,073,524", "J": "m", "S": 758}, {"I": "zQ82KAoOG0M", "M": 2156, "Y": 116, "P": 758, "K": 541, "D": "2:34:38", "V": "435,032", "J": "m", "S": 758}, {"I": "Ao5dhI1e8Qk", "M": 2156, "Y": 116, "P": 758, "K": 541, "D": "2:34:24", "V": "9,132", "J": "s", "S": 758}, {"I": "gQcERj6RvtI", "M": 2156, "Y": 116, "P": 758, "K": 541, "D": "2:34:38", "V": "6,346", "J": "h", "S": 758}, {"I": "sCGiv6I89wE", "M": 2156, "Y": 116, "P": 758, "K": 541, "D": "2:12:57", "V": "22", "J": "s", "S": 758}], "folders": [["movie", 7230, "0,1"], ["movie", 7220, "2"], ["movie", 1875, "3,4,5,6"], ["movie", 5113, "7,8"], ["movie", 2156, "9,10,11,12,13"]], "languages": {"english": "0,1,2,3,4", "tamil": "0,1,3,2,4", "telugu": "0,1,3,2,4", "kannada": "0,1,3,2,4", "malayalam": "0,1,3,2,4", "hindi": "0,1,3,2,4", "marathi": "0,1,3,2,4", "bengali": "0,1,3,2,4", "gujarati": "0,1,3,2,4", "punjabi": "0,1,3,2,4", "odia": "0,1,3,2,4", "assamese": "0,1,3,2,4"}}