{"stats": [{"H": "Videos", "C": "4"}, {"H": "Movies", "C": "4"}, {"H": "Years", "C": "3"}, {"H": "Duration", "C": "9 H"}, {"H": "Views", "C": "2 M"}], "poster": {"P": "Images/person.jpg"}, "title": {"T": 936, "H": "Tabu", "V": "tabu", "I": "person-fill"}, "movies": [{"I": "FAI7f4BwUbw", "M": 6442, "Y": 98, "P": 936, "K": 326, "D": "2:32:51", "V": "71", "J": "s", "S": 1225}, {"I": "6TDJ-b9lAOo", "M": 6240, "Y": 101, "P": 936, "K": 1661, "D": "2:31:39", "V": "677,416", "J": "m", "S": 95}, {"I": "IzUqHvztHiw", "M": 3623, "Y": 101, "P": 936, "K": 772, "D": "2:18:58", "V": "2,132", "J": "s", "S": 4235}, {"I": "dnn69TO4BfM", "M": 884, "Y": 99, "P": 936, "K": 33, "D": "2:31:16", "V": "441,959", "J": "h", "S": 936}], "folders": [["movie", 6442, "0"], ["movie", 6240, "1"], ["movie", 3623, "2"], ["movie", 884, "3"]], "languages": {"english": "0,1,2,3", "tamil": "0,1,3,2", "telugu": "0,1,3,2", "kannada": "0,1,3,2", "malayalam": "0,1,3,2", "hindi": "0,1,3,2", "marathi": "0,1,3,2", "bengali": "0,1,3,2", "gujarati": "0,1,3,2", "punjabi": "0,1,3,2", "odia": "0,1,3,2", "assamese": "0,1,3,2"}}