{"stats": [{"H": "Videos", "C": "7"}, {"H": "Movies", "C": "1"}, {"H": "Years", "C": "1"}, {"H": "Duration", "C": "15 H"}, {"H": "Views", "C": "3 M"}], "poster": {"P": "Images/director.jpg"}, "title": {"T": 4889, "H": "Ramchandar", "V": "rAmchaMdar", "I": "person-lines-fill"}, "movies": [{"I": "vUq46U5xzpM", "M": 1236, "Y": 96, "P": 1014, "K": 4889, "D": "2:09:41", "V": "1,693,749", "J": "m", "S": 131}, {"I": "2GfesBOttls", "M": 1236, "Y": 96, "P": 1014, "K": 4889, "D": "2:09:42", "V": "473,921", "J": "m", "S": 131}, {"I": "LYTols6CK4g", "M": 1236, "Y": 96, "P": 1014, "K": 4889, "D": "2:09:35", "V": "190,588", "J": "h", "S": 131}, {"I": "ZNgQLH4vnDg", "M": 1236, "Y": 96, "P": 1014, "K": 4889, "D": "2:08:25", "V": "148,260", "J": "m", "S": 131}, {"I": "8tELPZ5uFUg", "M": 1236, "Y": 96, "P": 1014, "K": 4889, "D": "2:09:25", "V": "72,463", "J": "m", "S": 131}, {"I": "oFmk61fmWuY", "M": 1236, "Y": 96, "P": 1014, "K": 4889, "D": "2:09:18", "V": "506", "J": "m", "S": 131}, {"I": "TxpfIOQ8B0c", "M": 1236, "Y": 96, "P": 1014, "K": 4889, "D": "2:09:18", "V": "376", "J": "s", "S": 131}], "folders": [["movie", 1236, "0,1,2,3,4,5,6"]], "languages": {"english": "0", "tamil": "0", "telugu": "0", "kannada": "0", "malayalam": "0", "hindi": "0", "marathi": "0", "bengali": "0", "gujarati": "0", "punjabi": "0", "odia": "0", "assamese": "0"}}